netsim_wrapper/__init__.py
netsim_wrapper/netsim2.py
netsim_wrapper-3.1.2.dist-info/LICENSE
netsim_wrapper-3.1.2.dist-info/METADATA
netsim_wrapper-3.1.2.dist-info/WHEEL
netsim_wrapper-3.1.2.dist-info/entry_points.txt
netsim_wrapper-3.1.2.dist-info/top_level.txt
netsim_wrapper-3.1.2.dist-info/RECORD
