Metadata-Version: 2.1
Name: netsim-wrapper
Version: 3.1.2
Summary: netsim-wrapper is a wrapper of ncs-netsim tool with added features.
Home-page: https://github.com/kirankotari/netsim-wrapper.git
Author: Kiran Kumar Kotari
Author-email: kirankotari@live.com
License: UNKNOWN
Keywords: ncs-netsim,netsim-wrapper,ncs-netsim2,delete netsim device
Platform: UNKNOWN
Classifier: Development Status :: 5 - Production/Stable
Classifier: Intended Audience :: Developers
Classifier: Topic :: Software Development :: Build Tools
Classifier: License :: OSI Approved :: MIT License
Classifier: Operating System :: OS Independent
Classifier: Programming Language :: Python :: 2.7
Classifier: Programming Language :: Python :: 3.5
Classifier: Programming Language :: Python :: 3.6
Classifier: Programming Language :: Python :: 3.7
Requires-Dist: pyyaml
